geoacumen_city/__init__.py
geoacumen_city/db/.gitkeep
geoacumen_city/db/dbip-city-lite-latest.mmdb
python_geoacumen_city-2023.4.15.dist-info/LICENSE
python_geoacumen_city-2023.4.15.dist-info/METADATA
python_geoacumen_city-2023.4.15.dist-info/WHEEL
python_geoacumen_city-2023.4.15.dist-info/top_level.txt
python_geoacumen_city-2023.4.15.dist-info/RECORD
