Metadata-Version: 2.1
Name: python-geoacumen-city
Version: 2023.4.15
Summary: Library to access/distribute DB-IP IP to City Lite Database
Home-page: UNKNOWN
Author: Kevin Chung
Author-email: kchung@nyu.edu
License: Apache 2.0
Platform: UNKNOWN
